nesim/__init__.py
nesim/devices/__init__.py
nesim/devices/cable.py
nesim/devices/device.py
nesim/devices/error_detection.py
nesim/devices/frame_sender.py
nesim/devices/host.py
nesim/devices/hub.py
nesim/devices/ip_packet_sender.py
nesim/devices/multiple_port_device.py
nesim/devices/router.py
nesim/devices/send_receiver.py
nesim/devices/switch.py
nesim/devices/utils.py
nesim/frame.py
nesim/inst_parser.py
nesim/instructions.py
nesim/ip.py
nesim/simulation.py
nesim/utils.py
nesim-0.3.0.dist-info/LICENSE
nesim-0.3.0.dist-info/WHEEL
nesim-0.3.0.dist-info/METADATA
nesim-0.3.0.dist-info/RECORD
