Metadata-Version: 2.1
Name: nesim
Version: 0.3.0
Summary: Paquete de python que permite simular de una red de computadoras.
Home-page: https://github.com/jmorgadov/nesim
License: MIT
Author: Jorge Morgado Vega
Author-email: jorge.morgadov@gmail.com
Requires-Python: >=3.7,<4.0
Classifier: License :: OSI Approved :: MIT License
Classifier: Programming Language :: Python :: 3
Classifier: Programming Language :: Python :: 3.7
Classifier: Programming Language :: Python :: 3.8
Classifier: Programming Language :: Python :: 3.9
Project-URL: Repository, https://github.com/jmorgadov/nesim
